task1/counter.sv
module counter#(
    parameter WIDTH = 8
)(
    //interface signals
    input logic clk,    //clock
    input logic rst,    //reset
    input logic en,    //counter enable
    output logic [WIDTH-1:0] count   //count output
);

always_ff @(posedge clk, posedge rst)
if(rst) count <={WIDTH{1'b0}};
else    count <=count+{{(WIDTH-1){1'b0}},en};  

    
endmodule

task1/counter.vcd
$version Generated by VerilatedVcd $end
$date Tue Oct 25 20:50:27 2022
 $end
$timescale   1ps $end

 $scope module TOP $end
  $var wire  1 # clk $end
  $var wire  8 & count [7:0] $end
  $var wire  1 % en $end
  $var wire  1 $ rst $end
  $scope module counter $end
   $var wire 32 ' WIDTH [31:0] $end
   $var wire  1 # clk $end
   $var wire  8 & count [7:0] $end
   $var wire  1 % en $end
   $var wire  1 $ rst $end
  $upscope $end
 $upscope $end
$enddefinitions $end


#0
0#
1$
0%
b00000000 &
b00000000000000000000000000001000 '
#1
1#
#2
0#
#3
1#
#4
0#
#5
1#
#6
0#
0$
#7
1#
#8
0#
#9
1#
#10
0#
#11
1#
#12
0#
1%
#13
1#
b00000001 &
#14
0#
#15
1#
b00000010 &
#16
0#
#17
1#
b00000011 &
#18
0#
#19
1#
b00000100 &
#20
0#
#21
1#
b00000101 &
#22
0#
#23
1#
b00000110 &
#24
0#
#25
1#
b00000111 &
#26
0#
#27
1#
b00001000 &
#28
0#
#29
1#
b00001001 &
#30
0#
0%
#31
1#
#32
0#
#33
1#
#34
0#
#35
1#
#36
0#
1%
#37
1#
b00001010 &
#38
0#
#39
1#
b00001011 &
#40
0#
#41
1#
b00001100 &
#42
0#
#43
1#
b00001101 &
#44
0#
#45
1#
b00001110 &
#46
0#
#47
1#
b00001111 &
#48
0#
#49
1#
b00010000 &
#50
0#
#51
1#
b00010001 &
#52
0#
#53
1#
b00010010 &
#54
0#
#55
1#
b00010011 &
#56
0#
#57
1#
b00010100 &
#58
0#
#59
1#
b00010101 &
#60
0#
#61
1#
b00010110 &
#62
0#
#63
1#
b00010111 &
#64
0#
#65
1#
b00011000 &
#66
0#
#67
1#
b00011001 &
#68
0#
#69
1#
b00011010 &
#70
0#
#71
1#
b00011011 &
#72
0#
#73
1#
b00011100 &
#74
0#
#75
1#
b00011101 &
#76
0#
#77
1#
b00011110 &
#78
0#
#79
1#
b00011111 &
#80
0#
#81
1#
b00100000 &
#82
0#
#83
1#
b00100001 &
#84
0#
#85
1#
b00100010 &
#86
0#
#87
1#
b00100011 &
#88
0#
#89
1#
b00100100 &
#90
0#
#91
1#
b00100101 &
#92
0#
#93
1#
b00100110 &
#94
0#
#95
1#
b00100111 &
#96
0#
#97
1#
b00101000 &
#98
0#
#99
1#
b00101001 &
#100
0#
#101
1#
b00101010 &
#102
0#
#103
1#
b00101011 &
#104
0#
#105
1#
b00101100 &
#106
0#
#107
1#
b00101101 &
#108
0#
#109
1#
b00101110 &
#110
0#
#111
1#
b00101111 &
#112
0#
#113
1#
b00110000 &
#114
0#
#115
1#
b00110001 &
#116
0#
#117
1#
b00110010 &
#118
0#
#119
1#
b00110011 &
#120
0#
#121
1#
b00110100 &
#122
0#
#123
1#
b00110101 &
#124
0#
#125
1#
b00110110 &
#126
0#
#127
1#
b00110111 &
#128
0#
#129
1#
b00111000 &
#130
0#
#131
1#
b00111001 &
#132
0#
#133
1#
b00111010 &
#134
0#
#135
1#
b00111011 &
#136
0#
#137
1#
b00111100 &
#138
0#
#139
1#
b00111101 &
#140
0#
#141
1#
b00111110 &
#142
0#
#143
1#
b00111111 &
#144
0#
#145
1#
b01000000 &
#146
0#
#147
1#
b01000001 &
#148
0#
#149
1#
b01000010 &
#150
0#
#151
1#
b01000011 &
#152
0#
#153
1#
b01000100 &
#154
0#
#155
1#
b01000101 &
#156
0#
#157
1#
b01000110 &
#158
0#
#159
1#
b01000111 &
#160
0#
#161
1#
b01001000 &
#162
0#
#163
1#
b01001001 &
#164
0#
#165
1#
b01001010 &
#166
0#
#167
1#
b01001011 &
#168
0#
#169
1#
b01001100 &
#170
0#
#171
1#
b01001101 &
#172
0#
#173
1#
b01001110 &
#174
0#
#175
1#
b01001111 &
#176
0#
#177
1#
b01010000 &
#178
0#
#179
1#
b01010001 &
#180
0#
#181
1#
b01010010 &
#182
0#
#183
1#
b01010011 &
#184
0#
#185
1#
b01010100 &
#186
0#
#187
1#
b01010101 &
#188
0#
#189
1#
b01010110 &
#190
0#
#191
1#
b01010111 &
#192
0#
#193
1#
b01011000 &
#194
0#
#195
1#
b01011001 &
#196
0#
#197
1#
b01011010 &
#198
0#
#199
1#
b01011011 &
#200
0#
#201
1#
b01011100 &
#202
0#
#203
1#
b01011101 &
#204
0#
#205
1#
b01011110 &
#206
0#
#207
1#
b01011111 &
#208
0#
#209
1#
b01100000 &
#210
0#
#211
1#
b01100001 &
#212
0#
#213
1#
b01100010 &
#214
0#
#215
1#
b01100011 &
#216
0#
#217
1#
b01100100 &
#218
0#
#219
1#
b01100101 &
#220
0#
#221
1#
b01100110 &
#222
0#
#223
1#
b01100111 &
#224
0#
#225
1#
b01101000 &
#226
0#
#227
1#
b01101001 &
#228
0#
#229
1#
b01101010 &
#230
0#
#231
1#
b01101011 &
#232
0#
#233
1#
b01101100 &
#234
0#
#235
1#
b01101101 &
#236
0#
#237
1#
b01101110 &
#238
0#
#239
1#
b01101111 &
#240
0#
#241
1#
b01110000 &
#242
0#
#243
1#
b01110001 &
#244
0#
#245
1#
b01110010 &
#246
0#
#247
1#
b01110011 &
#248
0#
#249
1#
b01110100 &
#250
0#
#251
1#
b01110101 &
#252
0#
#253
1#
b01110110 &
#254
0#
#255
1#
b01110111 &
#256
0#
#257
1#
b01111000 &
#258
0#
#259
1#
b01111001 &
#260
0#
#261
1#
b01111010 &
#262
0#
#263
1#
b01111011 &
#264
0#
#265
1#
b01111100 &
#266
0#
#267
1#
b01111101 &
#268
0#
#269
1#
b01111110 &
#270
0#
#271
1#
b01111111 &
#272
0#
#273
1#
b10000000 &
#274
0#
#275
1#
b10000001 &
#276
0#
#277
1#
b10000010 &
#278
0#
#279
1#
b10000011 &
#280
0#
#281
1#
b10000100 &
#282
0#
#283
1#
b10000101 &
#284
0#
#285
1#
b10000110 &
#286
0#
#287
1#
b10000111 &
#288
0#
#289
1#
b10001000 &
#290
0#
#291
1#
b10001001 &
#292
0#
#293
1#
b10001010 &
#294
0#
#295
1#
b10001011 &
#296
0#
#297
1#
b10001100 &
#298
0#
#299
1#
b10001101 &
#300
0#
#301
1#
b10001110 &
#302
0#
#303
1#
b10001111 &
#304
0#
#305
1#
b10010000 &
#306
0#
#307
1#
b10010001 &
#308
0#
#309
1#
b10010010 &
#310
0#
#311
1#
b10010011 &
#312
0#
#313
1#
b10010100 &
#314
0#
#315
1#
b10010101 &
#316
0#
#317
1#
b10010110 &
#318
0#
#319
1#
b10010111 &
#320
0#
#321
1#
b10011000 &
#322
0#
#323
1#
b10011001 &
#324
0#
#325
1#
b10011010 &
#326
0#
#327
1#
b10011011 &
#328
0#
#329
1#
b10011100 &
#330
0#
#331
1#
b10011101 &
#332
0#
#333
1#
b10011110 &
#334
0#
#335
1#
b10011111 &
#336
0#
#337
1#
b10100000 &
#338
0#
#339
1#
b10100001 &
#340
0#
#341
1#
b10100010 &
#342
0#
#343
1#
b10100011 &
#344
0#
#345
1#
b10100100 &
#346
0#
#347
1#
b10100101 &
#348
0#
#349
1#
b10100110 &
#350
0#
#351
1#
b10100111 &
#352
0#
#353
1#
b10101000 &
#354
0#
#355
1#
b10101001 &
#356
0#
#357
1#
b10101010 &
#358
0#
#359
1#
b10101011 &
#360
0#
#361
1#
b10101100 &
#362
0#
#363
1#
b10101101 &
#364
0#
#365
1#
b10101110 &
#366
0#
#367
1#
b10101111 &
#368
0#
#369
1#
b10110000 &
#370
0#
#371
1#
b10110001 &
#372
0#
#373
1#
b10110010 &
#374
0#
#375
1#
b10110011 &
#376
0#
#377
1#
b10110100 &
#378
0#
#379
1#
b10110101 &
#380
0#
#381
1#
b10110110 &
#382
0#
#383
1#
b10110111 &
#384
0#
#385
1#
b10111000 &
#386
0#
#387
1#
b10111001 &
#388
0#
#389
1#
b10111010 &
#390
0#
#391
1#
b10111011 &
#392
0#
#393
1#
b10111100 &
#394
0#
#395
1#
b10111101 &
#396
0#
#397
1#
b10111110 &
#398
0#
#399
1#
b10111111 &
#400
0#
#401
1#
b11000000 &
#402
0#
#403
1#
b11000001 &
#404
0#
#405
1#
b11000010 &
#406
0#
#407
1#
b11000011 &
#408
0#
#409
1#
b11000100 &
#410
0#
#411
1#
b11000101 &
#412
0#
#413
1#
b11000110 &
#414
0#
#415
1#
b11000111 &
#416
0#
#417
1#
b11001000 &
#418
0#
#419
1#
b11001001 &
#420
0#
#421
1#
b11001010 &
#422
0#
#423
1#
b11001011 &
#424
0#
#425
1#
b11001100 &
#426
0#
#427
1#
b11001101 &
#428
0#
#429
1#
b11001110 &
#430
0#
#431
1#
b11001111 &
#432
0#
#433
1#
b11010000 &
#434
0#
#435
1#
b11010001 &
#436
0#
#437
1#
b11010010 &
#438
0#
#439
1#
b11010011 &
#440
0#
#441
1#
b11010100 &
#442
0#
#443
1#
b11010101 &
#444
0#
#445
1#
b11010110 &
#446
0#
#447
1#
b11010111 &
#448
0#
#449
1#
b11011000 &
#450
0#
#451
1#
b11011001 &
#452
0#
#453
1#
b11011010 &
#454
0#
#455
1#
b11011011 &
#456
0#
#457
1#
b11011100 &
#458
0#
#459
1#
b11011101 &
#460
0#
#461
1#
b11011110 &
#462
0#
#463
1#
b11011111 &
#464
0#
#465
1#
b11100000 &
#466
0#
#467
1#
b11100001 &
#468
0#
#469
1#
b11100010 &
#470
0#
#471
1#
b11100011 &
#472
0#
#473
1#
b11100100 &
#474
0#
#475
1#
b11100101 &
#476
0#
#477
1#
b11100110 &
#478
0#
#479
1#
b11100111 &
#480
0#
#481
1#
b11101000 &
#482
0#
#483
1#
b11101001 &
#484
0#
#485
1#
b11101010 &
#486
0#
#487
1#
b11101011 &
#488
0#
#489
1#
b11101100 &
#490
0#
#491
1#
b11101101 &
#492
0#
#493
1#
b11101110 &
#494
0#
#495
1#
b11101111 &
#496
0#
#497
1#
b11110000 &
#498
0#
#499
1#
b11110001 &
#500
0#
#501
1#
b11110010 &
#502
0#
#503
1#
b11110011 &
#504
0#
#505
1#
b11110100 &
#506
0#
#507
1#
b11110101 &
#508
0#
#509
1#
b11110110 &
#510
0#
#511
1#
b11110111 &
#512
0#
#513
1#
b11111000 &
#514
0#
#515
1#
b11111001 &
#516
0#
#517
1#
b11111010 &
#518
0#
#519
1#
b11111011 &
#520
0#
#521
1#
b11111100 &
#522
0#
#523
1#
b11111101 &
#524
0#
#525
1#
b11111110 &
#526
0#
#527
1#
b11111111 &
#528
0#
#529
1#
b00000000 &
#530
0#
#531
1#
b00000001 &
#532
0#
#533
1#
b00000010 &
#534
0#
#535
1#
b00000011 &
#536
0#
#537
1#
b00000100 &
#538
0#
#539
1#
b00000101 &
#540
0#
#541
1#
b00000110 &
#542
0#
#543
1#
b00000111 &
#544
0#
#545
1#
b00001000 &
#546
0#
#547
1#
b00001001 &
#548
0#
#549
1#
b00001010 &
#550
0#
#551
1#
b00001011 &
#552
0#
#553
1#
b00001100 &
#554
0#
#555
1#
b00001101 &
#556
0#
#557
1#
b00001110 &
#558
0#
#559
1#
b00001111 &
#560
0#
#561
1#
b00010000 &
#562
0#
#563
1#
b00010001 &
#564
0#
#565
1#
b00010010 &
#566
0#
#567
1#
b00010011 &
#568
0#
#569
1#
b00010100 &
#570
0#
#571
1#
b00010101 &
#572
0#
#573
1#
b00010110 &
#574
0#
#575
1#
b00010111 &
#576
0#
#577
1#
b00011000 &
#578
0#
#579
1#
b00011001 &
#580
0#
#581
1#
b00011010 &
#582
0#
#583
1#
b00011011 &
#584
0#
#585
1#
b00011100 &
#586
0#
#587
1#
b00011101 &
#588
0#
#589
1#
b00011110 &
#590
0#
#591
1#
b00011111 &
#592
0#
#593
1#
b00100000 &
#594
0#
#595
1#
b00100001 &
#596
0#
#597
1#
b00100010 &
#598
0#
#599
1#
b00100011 &
